CHANGES.rst
MANIFEST.in
README.rst
jsonquery.py
setup.cfg
setup.py
jsonquery.egg-info/PKG-INFO
jsonquery.egg-info/SOURCES.txt
jsonquery.egg-info/dependency_links.txt
jsonquery.egg-info/requires.txt
jsonquery.egg-info/top_level.txt