Metadata-Version: 1.1
Name: jsonquery
Version: 1.0.1
Summary: Basic json -> sqlalchemy query builder
Home-page: http://jsonquery.readthedocs.org/
Author: Joe Cross
Author-email: joe.mcross@gmail.com
License: MIT
Keywords: json sqlalchemy sql orm
Platform: any
Classifier: Development Status :: 5 - Production/Stable
Classifier: Intended Audience :: Developers
Classifier: License :: OSI Approved :: MIT License
Classifier: Operating System :: OS Independent
Classifier: Programming Language :: Python
Classifier: Programming Language :: Python :: 2
Classifier: Programming Language :: Python :: 2.6
Classifier: Programming Language :: Python :: 2.7
Classifier: Programming Language :: Python :: 3
Classifier: Programming Language :: Python :: 3.2
Classifier: Programming Language :: Python :: 3.3
Classifier: Programming Language :: Python :: 3.4
Classifier: Topic :: Software Development :: Libraries
Classifier: Topic :: Software Development :: Libraries :: Python Modules
